renderlytic/__init__.py
renderlytic/server.py
mcp_renderlytic-0.1.6.dist-info/METADATA
mcp_renderlytic-0.1.6.dist-info/WHEEL
mcp_renderlytic-0.1.6.dist-info/entry_points.txt
mcp_renderlytic-0.1.6.dist-info/RECORD
