Metadata-Version: 2.4
Name: mcp-renderlytic
Version: 0.1.6
Summary: Renderlytic is a headless CMS that empowers users to create and manage their blog content, which can then be seamlessly integrated into various AI-powered clients and web applications, rendering as static HTML.
Project-URL: Homepage, https://wistify.app
Requires-Python: >=3.11
Requires-Dist: mcp[cli]>=1.5.0
Requires-Dist: requests>=2.32.3
